[
  {
    "Type": "BodySetup",
    "Name": "BodySetup_0",
    "Outer": "AircraftFighterW_Dam_Tail",
    "Class": "UScriptClass'BodySetup'",
    "Properties": {
      "DefaultInstance": {
        "ObjectType": "ECC_WorldStatic",
        "CollisionProfileName": "BlockAll",
        "CollisionResponses": {
          "ResponseArray": [
            {
              "Channel": "Damage",
              "Response": "ECR_Overlap"
            },
            {
              "Channel": "BuildSurface",
              "Response": "ECR_Overlap"
            }
          ]
        }
      }
    },
    "BodySetupGuid": "6E398BBE496C28E0E3233A9C08B6981A",
    "CookedFormatData": {
      "PhysXPC": {
        "BulkDataFlags": "BULKDATA_SingleUse | BULKDATA_ForceInlinePayload",
        "ElementCount": 85822,
        "SizeOnDisk": 85822,
        "OffsetInFile": "0x6EF4A"
      }
    }
  },
  {
    "Type": "NavCollision",
    "Name": "NavCollision_0",
    "Outer": "AircraftFighterW_Dam_Tail",
    "Class": "UScriptClass'NavCollision'",
    "CookedFormatData": {
      "NavCollision_X": {
        "BulkDataFlags": "BULKDATA_SingleUse | BULKDATA_ForceInlinePayload",
        "ElementCount": 21,
        "SizeOnDisk": 21,
        "OffsetInFile": "0x83ED0"
      }
    }
  },
  {
    "Type": "StaticMesh",
    "Name": "AircraftFighterW_Dam_Tail",
    "Class": "UScriptClass'StaticMesh'",
    "Properties": {
      "StaticMaterials": [
        {
          "MaterialInterface": {
            "ObjectName": "MaterialInstanceConstant'AircraftFighterW'",
            "ObjectPath": "War/Content/Blueprints/Vehicles/Aircraft/AircraftFighterW/Materials/AircraftFighterW.0"
          },
          "MaterialSlotName": "AircraftFighterW",
          "ImportedMaterialSlotName": "AircraftFighterW",
          "UVChannelData": {
            "bInitialized": true,
            "bOverrideDensities": false,
            "LocalUVDensities": 1100.4164,
            "LocalUVDensities[1]": 0.0,
            "LocalUVDensities[2]": 0.0,
            "LocalUVDensities[3]": 0.0
          }
        },
        {
          "MaterialInterface": {
            "ObjectName": "MaterialInstanceConstant'AircraftFighterWDetail'",
            "ObjectPath": "War/Content/Blueprints/Vehicles/Aircraft/AircraftFighterW/Materials/AircraftFighterWDetail.0"
          },
          "MaterialSlotName": "AircraftFighterWDetail",
          "ImportedMaterialSlotName": "AircraftFighterWDetail",
          "UVChannelData": {
            "bInitialized": true,
            "bOverrideDensities": false,
            "LocalUVDensities": 338.8784,
            "LocalUVDensities[1]": 0.0,
            "LocalUVDensities[2]": 0.0,
            "LocalUVDensities[3]": 0.0
          }
        },
        {
          "MaterialInterface": {
            "ObjectName": "MaterialInstanceConstant'AircraftFighterWDetail'",
            "ObjectPath": "War/Content/Blueprints/Vehicles/Aircraft/AircraftFighterW/Materials/AircraftFighterWDetail.0"
          },
          "MaterialSlotName": "KioskTrims",
          "ImportedMaterialSlotName": "KioskTrims",
          "UVChannelData": {
            "bInitialized": true,
            "bOverrideDensities": false,
            "LocalUVDensities": 61.165176,
            "LocalUVDensities[1]": 0.0,
            "LocalUVDensities[2]": 0.0,
            "LocalUVDensities[3]": 0.0
          }
        }
      ],
      "LightmapUVDensity": 666.9191,
      "LightMapResolution": 64,
      "ExtendedBounds": {
        "Origin": {
          "X": 5.3204193,
          "Y": -470.91647,
          "Z": 123.53898
        },
        "BoxExtent": {
          "X": 161.24756,
          "Y": 164.55893,
          "Z": 90.35593
        },
        "SphereRadius": 183.33139
      }
    },
    "BodySetup": {
      "ObjectName": "BodySetup'AircraftFighterW_Dam_Tail:BodySetup_0'",
      "ObjectPath": "War/Content/Blueprints/Vehicles/Aircraft/AircraftFighterW/Meshes/AircraftFighterW_Dam_Tail.0"
    },
    "NavCollision": {
      "ObjectName": "NavCollision'AircraftFighterW_Dam_Tail:NavCollision_0'",
      "ObjectPath": "War/Content/Blueprints/Vehicles/Aircraft/AircraftFighterW/Meshes/AircraftFighterW_Dam_Tail.1"
    },
    "LightingGuid": "D249119D-4A6E4A0D-203A0FA9-EAE2807F",
    "RenderData": {
      "LODs": [
        {
          "Sections": [
            {
              "MaterialIndex": 0,
              "FirstIndex": 0,
              "NumTriangles": 869,
              "MinVertexIndex": 0,
              "MaxVertexIndex": 798,
              "bEnableCollision": true,
              "bCastShadow": true,
              "bForceOpaque": false,
              "bVisibleInRayTracing": true
            },
            {
              "MaterialIndex": 1,
              "FirstIndex": 2607,
              "NumTriangles": 138,
              "MinVertexIndex": 799,
              "MaxVertexIndex": 938,
              "bEnableCollision": true,
              "bCastShadow": true,
              "bForceOpaque": false,
              "bVisibleInRayTracing": true
            },
            {
              "MaterialIndex": 2,
              "FirstIndex": 3021,
              "NumTriangles": 2000,
              "MinVertexIndex": 939,
              "MaxVertexIndex": 3797,
              "bEnableCollision": true,
              "bCastShadow": true,
              "bForceOpaque": false,
              "bVisibleInRayTracing": true
            }
          ],
          "MaxDeviation": 0.0,
          "PositionVertexBuffer": {
            "Stride": 12,
            "NumVertices": 3798
          },
          "VertexBuffer": {
            "NumTexCoords": 1,
            "NumVertices": 3798,
            "Strides": -1,
            "UseHighPrecisionTangentBasis": false,
            "UseFullPrecisionUVs": false
          },
          "ColorVertexBuffer": {
            "Stride": 0,
            "NumVertices": 0
          }
        },
        {
          "Sections": [
            {
              "MaterialIndex": 0,
              "FirstIndex": 0,
              "NumTriangles": 424,
              "MinVertexIndex": 0,
              "MaxVertexIndex": 467,
              "bEnableCollision": true,
              "bCastShadow": true,
              "bForceOpaque": false,
              "bVisibleInRayTracing": true
            },
            {
              "MaterialIndex": 1,
              "FirstIndex": 1272,
              "NumTriangles": 47,
              "MinVertexIndex": 468,
              "MaxVertexIndex": 530,
              "bEnableCollision": true,
              "bCastShadow": true,
              "bForceOpaque": false,
              "bVisibleInRayTracing": true
            },
            {
              "MaterialIndex": 2,
              "FirstIndex": 1413,
              "NumTriangles": 1032,
              "MinVertexIndex": 531,
              "MaxVertexIndex": 2206,
              "bEnableCollision": true,
              "bCastShadow": true,
              "bForceOpaque": false,
              "bVisibleInRayTracing": true
            }
          ],
          "MaxDeviation": 6.2438927,
          "PositionVertexBuffer": {
            "Stride": 12,
            "NumVertices": 2207
          },
          "VertexBuffer": {
            "NumTexCoords": 1,
            "NumVertices": 2207,
            "Strides": -1,
            "UseHighPrecisionTangentBasis": false,
            "UseFullPrecisionUVs": false
          },
          "ColorVertexBuffer": {
            "Stride": 0,
            "NumVertices": 0
          }
        }
      ],
      "Bounds": {
        "Origin": {
          "X": 5.3204193,
          "Y": -470.91647,
          "Z": 123.53898
        },
        "BoxExtent": {
          "X": 161.24756,
          "Y": 164.55893,
          "Z": 90.35593
        },
        "SphereRadius": 183.33139
      },
      "bLODsShareStaticLighting": true,
      "ScreenSize": [
        1.0,
        0.5591008,
        0.0,
        0.0,
        0.0,
        0.0,
        0.0,
        0.0
      ]
    }
  }
]